diffusivity/VERSION
diffusivity/__init__.py
diffusivity/__main__.py
diffusivity/cli.py
diffusivity/diffusion_coefficients.py
diffusivity/process.py
diffusivity/utilities.py
diffusivity/vasp_md_rename.py
diffusivity/version.py
diffusivity-0.1.1.dist-info/LICENSE
diffusivity-0.1.1.dist-info/METADATA
diffusivity-0.1.1.dist-info/WHEEL
diffusivity-0.1.1.dist-info/entry_points.txt
diffusivity-0.1.1.dist-info/top_level.txt
diffusivity-0.1.1.dist-info/RECORD
