Metadata-Version: 2.1
Name: diffusivity
Version: 0.1.1
Summary: diffusivity calculates the diffusion properties by processing trajectory files
Home-page: https://github.com/sheriftawfikabbas/diffusivity
Author: Sherif Abdulkader Tawfik Abbas
Author-email: sherif.tawfic@gmail.com
License: mit
Keywords: material science,simulation
License-File: LICENSE
Requires-Dist: ase
Requires-Dist: pandas
Requires-Dist: numpy
